{
    "actions": [
        {
            "shortName": "Bar",
            "name": "mtp.barek",
            "parentAction": "MTP",
            "startDate": "15-05-2022",
            "endDate": "30-06-2023",
            "place": "mtp.place",
            "description": "mtp.bar.dsc"
        },
        {
            "shortName": "Pacz",
            "name": "Ua.pack",
            "parentAction": null,
            "startDate": "15-05-2022",
            "endDate": "30-06-2023",
            "place": "mtp.place",
            "description": "ua.pack.dsc",
            "reaction": ":)"
        },
        {
            "shortName": "Inf",
            "name": "mtp.info",
            "parentAction": "MTP",
            "startDate": "15-05-2022",
            "endDate": "30-06-2023",
            "place": "mtp.place",
            "description": "mtp.info.dsc"
        }
    ]
}
